querySDSS
