Metadata-Version: 2.1
Name: querySDSS
Version: 1.8
Summary: Query for SDSS datarelease 18
Home-page: https://github.com/aCosmicDebugger/querySDSS
Author: aCosmicDebbuger
Author-email: acosmicdebugger@gmail.com
License: MIT
Keywords: example project
Platform: UNKNOWN
